{
  "manualInputQuickActionLabel": {
    "en": "Manual entry",
    "de": "Manuelle Eingabe",
    "es": "Registro manual",
    "fr": "Saisie manuelle",
    "it": "Inserimento manuale",
    "ja": "手入力",
    "kr": "직접 입력",
    "nl": "Handmatige invoer",
    "ur": "دستی اندراج",
    "ru": "Ручной ввод",
    "uk": "Ручне введення",
    "zh": "手动输入",
    "zh_TW": "手動輸入",
    "vi": "Nhập thủ công"
  },
  "onboardingQuestionHelpMost": {
    "en": "What do you want help with most?",
    "de": "Wobei können wir dir am meisten helfen?",
    "es": "¿En qué necesitas más ayuda?",
    "fr": "Quel est votre objectif principal ?",
    "it": "In cosa desideri ricevere più aiuto?",
    "ja": "どのようなサポートが一番必要ですか？",
    "kr": "어떤 도움을 가장 필요로 하시나요?",
    "nl": "Waarmee kunnen we je het beste helpen?",
    "ur": "آپ کو کس چیز میں سب سے زیادہ مدد چاہیے؟",
    "ru": "С чем вам важнее всего помочь?",
    "uk": "З чим вам найбільше потрібна допомога?",
    "zh": "您最希望在哪些方面获得帮助？",
    "zh_TW": "您最希望在哪些方面獲得幫助？",
    "vi": "Bạn cần giúp đỡ điều gì nhất?"
  },
  "onboardingQuestionWhoBudgetWith": {
    "en": "Who do you usually budget with?",
    "de": "Mit wem budgetierst du normalerweise?",
    "es": "¿Con quién sueles gestionar tu presupuesto?",
    "fr": "Avec qui gérez-vous votre budget habituellement ?",
    "it": "Con chi gestisci solitamente il tuo budget?",
    "ja": "普段は誰と一緒に予算を管理していますか？",
    "kr": "평소에 누구와 함께 가계부를 관리하시나요?",
    "nl": "Met wie beheer je meestal je budget?",
    "ur": "آپ عام طور پر بجٹ کس کے ساتھ بناتے ہیں؟",
    "ru": "С кем вы обычно ведете бюджет?",
    "uk": "З ким ви зазвичай ведете бюджет?",
    "zh": "您通常和谁一起管理预算？",
    "zh_TW": "您通常和誰一起管理預算？",
    "vi": "Bạn thường quản lý ngân sách cùng với ai?"
  },
  "onboardingQuestionSplitBills": {
    "en": "Do you split bills with someone?",
    "de": "Teilst du Rechnungen mit jemandem?",
    "es": "¿Compartes gastos con alguien?",
    "fr": "Partagez-vous vos frais avec quelqu'un ?",
    "it": "Dividi le spese con qualcuno?",
    "ja": "誰かと割り勘をしていますか？",
    "kr": "누군가와 비용을 나누어 내시나요?",
    "nl": "Deel je de rekeningen met iemand?",
    "ur": "کیا آپ کسی کے ساتھ بل بانٹتے ہیں؟",
    "ru": "Вы делите с кем-то расходы?",
    "uk": "Ви ділите з кимось витрати?",
    "zh": "你会和别人分摊账单吗？",
    "zh_TW": "你會和別人分攤帳單嗎？",
    "vi": "Bạn có chia sẻ hóa đơn với ai không?"
  },
  "onboardingQuestionMonthlyAmount": {
    "en": "How much money are you planning with this month?",
    "de": "Wie hoch ist dein Budget für diesen Monat?",
    "es": "¿Con cuánto dinero cuentas para este mes?",
    "fr": "Quel montant prévoyez-vous pour ce mois-ci ?",
    "it": "Quanto denaro prevedi di gestire questo mese?",
    "ja": "今月の予算はいくらですか？",
    "kr": "이번 달에는 얼마로 예산을 세우실 건가요?",
    "nl": "Met hoeveel geld plan je deze maand?",
    "ur": "اس مہینے آپ کتنی رقم کی منصوبہ بندی کر رہے ہیں؟",
    "ru": "Какой суммой вы планируете распоряжаться в этом месяце?",
    "uk": "Яку суму ви плануєте витратити цього місяця?",
    "zh": "这个月你打算规划多少资金？",
    "zh_TW": "這個月你打算規劃多少資金？",
    "vi": "Bạn dự định chi tiêu bao nhiêu trong tháng này?"
  },
  "onboardingQuestionHousing": {
    "en": "Housing: what do you pay each month?",
    "de": "Wohnen: Was zahlst du jeden Monat?",
    "es": "Vivienda: ¿cuánto pagas cada mes?",
    "fr": "Logement : combien payez-vous chaque mois ?",
    "it": "Casa: quanto paghi ogni mese?",
    "ja": "住居費：毎月いくら支払っていますか？",
    "kr": "주거비: 매달 얼마를 지불하시나요?",
    "nl": "Wonen: wat betaal je elke maand?",
    "ur": "رہائش: آپ ہر ماہ کتنا ادا کرتے ہیں؟",
    "ru": "Жилье: сколько вы платите каждый месяц?",
    "uk": "Житло: скільки ви платите щомісяця?",
    "zh": "居住：你每个月支付多少费用？",
    "zh_TW": "居住：你每個月支付多少費用？",
    "vi": "Nhà ở: Bạn trả bao nhiêu mỗi tháng?"
  },
  "onboardingQuestionUtilities": {
    "en": "About how much are utilities each month?",
    "de": "Wie hoch sind deine Nebenkosten etwa?",
    "es": "¿A cuánto ascienden tus facturas de servicios?",
    "fr": "À combien s'élèvent vos charges environ ?",
    "it": "A quanto ammontano circa le utenze ogni mese?",
    "ja": "光熱費は毎月どのくらいですか？",
    "kr": "공과금은 한 달에 어느 정도인가요?",
    "nl": "Hoeveel betaal je ongeveer aan nutsvoorzieningen?",
    "ur": "ہر ماہ یوٹیلیٹیز کا خرچہ کتنا ہوتا ہے؟",
    "ru": "Сколько вы обычно тратите на коммунальные услуги?",
    "uk": "Скільки приблизно ви витрачаєте на комунальні послуги?",
    "zh": "每个月的水电煤气费大约是多少？",
    "zh_TW": "每個月的水電煤氣費大約是多少？",
    "vi": "Tiền điện nước, tiện ích mỗi tháng khoảng bao nhiêu?"
  },
  "onboardingQuestionDebtMinimums": {
    "en": "Any minimum debt payments each month?",
    "de": "Hast du monatliche Mindesttilgungen?",
    "es": "¿Tienes pagos mínimos de deudas cada mes?",
    "fr": "Avez-vous des mensualités minimales de dettes ?",
    "it": "Hai delle rate minime da pagare ogni mese?",
    "ja": "毎月の借入返済（最低支払い額）はありますか？",
    "kr": "매달 지불해야 하는 최소 채무 상환액이 있나요?",
    "nl": "Heb je maandelijkse minimum aflossingen?",
    "ur": "کیا ہر ماہ قرض کی کوئی کم از کم ادائیگی ہے؟",
    "ru": "Есть ли минимальные платежи по долгам?",
    "uk": "Чи є у вас мінімальні щомісячні платежі за боргами?",
    "zh": "每个月是否有最低债务还款额？",
    "zh_TW": "每個月是否有最低債務還款額？",
    "vi": "Có khoản thanh toán nợ tối thiểu nào mỗi tháng không?"
  },
  "onboardingQuestionSetAside": {
    "en": "How much do you want to set aside this month?",
    "de": "Wie viel möchtest du diesen Monat zur Seite legen?",
    "es": "¿Cuánto quieres ahorrar o apartar este mes?",
    "fr": "Combien souhaitez-vous mettre de côté ce mois-ci ?",
    "it": "Quanto vuoi mettere da parte questo mese?",
    "ja": "今月はいくら貯金（取り分け）したいですか？",
    "kr": "이번 달에 따로 저축하고 싶은 금액은 얼마인가요?",
    "nl": "Hoeveel wil je deze maand opzij zetten?",
    "ur": "آپ اس مہینے کتنی رقم الگ رکھنا چاہتے ہیں؟",
    "ru": "Сколько вы хотите отложить в этом месяце?",
    "uk": "Скільки ви хочете відкласти цього місяця?",
    "zh": "这个月你打算存多少钱？",
    "zh_TW": "這個月你打算存多少錢？",
    "vi": "Bạn muốn để dành bao nhiêu trong tháng này?"
  },
  "onboardingQuestionEatOut": {
    "en": "How often do you eat out or order delivery?",
    "de": "Wie oft isst du auswärts oder bestellst Essen?",
    "es": "¿Qué tan seguido comes fuera o pides comida?",
    "fr": "À quelle fréquence mangez-vous dehors ou commandez-vous ?",
    "it": "Quanto spesso mangi fuori o ordini a domicilio?",
    "ja": "外食やデリバリーの頻度はどのくらいですか？",
    "kr": "외식이나 배달을 얼마나 자주 하시나요?",
    "nl": "Hoe vaak eet je buiten de deur of bestel je eten?",
    "ur": "آپ کتنی بار باہر کھانا کھاتے ہیں یا ڈیلیوری منگواتے ہیں؟",
    "ru": "Как часто вы едите вне дома или заказываете доставку?",
    "uk": "Як часто ви їсте поза домом або замовляєте доставку?",
    "zh": "你经常在外就餐或点外卖吗？",
    "zh_TW": "你經常在外就餐或點外賣嗎？",
    "vi": "Bạn có thường xuyên đi ăn ngoài hoặc đặt đồ ăn không?"
  },
  "onboardingQuestionSubscriptions": {
    "en": "Subscriptions & memberships",
    "de": "Abos & Mitgliedschaften",
    "es": "Suscripciones y membresías",
    "fr": "Abonnements et adhésions",
    "it": "Abbonamenti e iscrizioni",
    "ja": "サブスク・会費",
    "kr": "구독 및 멤버십",
    "nl": "Abonnementen & lidmaatschappen",
    "ur": "سبسکرپشنز اور ممبرشپ",
    "ru": "Подписки и членство",
    "uk": "Передплати та абонементи",
    "zh": "订阅与会员",
    "zh_TW": "訂閱與會員",
    "vi": "Gói đăng ký & thành viên"
  },
  "onboardingQuestionPets": {
    "en": "Do you have pets?",
    "de": "Hast du Haustiere?",
    "es": "¿Tienes mascotas?",
    "fr": "Avez-vous des animaux de compagnie ?",
    "it": "Hai animali domestici?",
    "ja": "ペットは飼っていますか？",
    "kr": "반려동물을 키우시나요?",
    "nl": "Heb je huisdieren?",
    "ur": "کیا آپ کے پاس پالتو جانور ہیں؟",
    "ru": "У вас есть домашние животные?",
    "uk": "Чи є у вас домашні тварини?",
    "zh": "你有宠物吗？",
    "zh_TW": "你有寵物嗎？",
    "vi": "Bạn có nuôi thú cưng không?"
  },
  "onboardingQuestionPetSpend": {
    "en": "How much do you usually spend on pets each month?",
    "de": "Wie viel gibst du monatlich für Haustiere aus?",
    "es": "¿Cuánto sueles gastar en tus mascotas al mes?",
    "fr": "Combien dépensez-vous pour vos animaux chaque mois ?",
    "it": "Quanto spendi solitamente per i tuoi animali ogni mese?",
    "ja": "ペットには毎月いくら使いますか？",
    "kr": "반려동물에게 매달 보통 얼마를 쓰시나요?",
    "nl": "Hoeveel geef je meestal uit aan je huisdieren?",
    "ur": "آپ عام طور پر ہر ماہ پالتو جانوروں پر کتنا خرچ کرتے ہیں؟",
    "ru": "Сколько вы обычно тратите на питомцев в месяц?",
    "uk": "Скільки ви зазвичай витрачаєте на тварин щомісяця?",
    "zh": "你通常每个月在宠物身上花多少钱？",
    "zh_TW": "你通常每個月在寵物身上花多少錢？",
    "vi": "Bạn thường chi bao nhiêu cho thú cưng mỗi tháng?"
  },
  "onboardingQuestionTransport": {
    "en": "How do you usually get around?",
    "de": "Wie bist du normalerweise unterwegs?",
    "es": "¿Cómo sueles desplazarte?",
    "fr": "Comment vous déplacez-vous habituellement ?",
    "it": "Come ti sposti solitamente?",
    "ja": "普段の移動手段は何ですか？",
    "kr": "평소 이동 수단은 무엇인가요?",
    "nl": "Hoe verplaats je je meestal?",
    "ur": "آپ عام طور پر کیسے سفر کرتے ہیں؟",
    "ru": "Как вы обычно передвигаетесь?",
    "uk": "Як ви зазвичай пересуваєтеся?",
    "zh": "你通常의出行方式是什么？",
    "zh_TW": "你通常的出行方式是什麼？",
    "vi": "Bạn thường di chuyển bằng phương tiện gì?"
  },
  "onboardingQuestionDependents": {
    "en": "Do you pay for kids or dependents?",
    "de": "Zahlst du für Kinder oder Angehörige?",
    "es": "¿Tienes gastos por hijos o dependientes?",
    "fr": "Avez-vous des enfants ou des personnes à charge ?",
    "it": "Sostieni spese per figli o persone a carico?",
    "ja": "子供や扶養家族の費用はありますか？",
    "kr": "자녀나 부양가족을 위해 지출하시나요?",
    "nl": "Betaal je voor kinderen of andere gezinsleden?",
    "ur": "کیا آپ بچوں یا زیر کفالت افراد کے اخراجات اٹھاتے ہیں؟",
    "ru": "У вас есть расходы на детей или иждивенцев?",
    "uk": "Чи є у вас витрати на дітей або утриманців?",
    "zh": "你需要抚养孩子或赡养家属吗？",
    "zh_TW": "你需要撫養孩子或贍養家屬嗎？",
    "vi": "Bạn có chi trả cho con cái hoặc người phụ thuộc không?"
  },
  "onboardingQuestionPlanAhead": {
    "en": "Anything big you want to plan ahead for?",
    "de": "Möchtest du für etwas Größeres vorausplanen?",
    "es": "¿Hay algo importante para lo que quieras ahorrar?",
    "fr": "Y a-t-il un projet important à planifier ?",
    "it": "Hai in programma qualche spesa importante?",
    "ja": "前もって準備しておきたい大きな予定はありますか？",
    "kr": "미리 계획하고 싶은 큰 지출이 있나요?",
    "nl": "Zijn er grote uitgaven waar je for wilt plannen?",
    "ur": "کیا کوئی بڑی چیز ہے جس کے لیے آپ پہلے سے منصوبہ بندی کرنا چاہتے ہیں؟",
    "ru": "Планируете ли вы какие-то крупные траты?",
    "uk": "Чи плануєте ви якісь великі витрати заздалегідь?",
    "zh": "有什么大额支出需要提前规划吗？",
    "zh_TW": "有什麼大額支出需要提前規劃嗎？",
    "vi": "Có sự kiện lớn nào bạn muốn lên kế hoạch trước không?"
  },
  "onboardingQuestionBreathingRoom": {
    "en": "How much breathing room do you want?",
    "de": "Wie viel Puffer möchtest du haben?",
    "es": "¿Cuánto margen de maniobra quieres tener?",
    "fr": "De quelle marge de manœuvre avez-vous besoin ?",
    "it": "Quanto margine di manovra vorresti avere?",
    "ja": "どのくらいの余裕（予備費）が欲しいですか？",
    "kr": "어느 정도의 여유 자금을 원하시나요?",
    "nl": "Hoeveel buffer wil je hebben?",
    "ur": "آپ کتنی گنجائش (بفر) رکھنا چاہتے ہیں؟",
    "ru": "Какой запас свободных средств вам нужен?",
    "uk": "Який запас коштів ви хочете мати?",
    "zh": "你想要预留多少缓冲资金？",
    "zh_TW": "你想要預留多少緩衝資金？",
    "vi": "Bạn muốn có bao nhiêu khoản dự phòng?"
  },
  "onboardingPreviewTotal": {
    "en": "Total money to plan with",
    "de": "Geplante Gesamtsumme",
    "es": "Total a planificar",
    "fr": "Total à planifier",
    "it": "Totale da pianificare",
    "ja": "計画する合計金額",
    "kr": "계획할 총 금액",
    "nl": "Totaal te plannen geld",
    "ur": "منصوبہ بندی کے لیے کل رقم",
    "ru": "Итого к планированию",
    "uk": "Загальна сума для планування",
    "zh": "待规划资金总额",
    "zh_TW": "待規劃資金總額",
    "vi": "Tổng số tiền cần lên kế hoạch"
  },
  "onboardingPreviewFixed": {
    "en": "Fixed costs you entered",
    "de": "Eingegebene Fixkosten",
    "es": "Gastos fijos ingresados",
    "fr": "Frais fixes saisis",
    "it": "Spese fisse inserite",
    "ja": "入力済みの固定費",
    "kr": "입력한 고정 지출",
    "nl": "Ingevoerde vaste lasten",
    "ur": "درج کردہ مقررہ اخراجات",
    "ru": "Введенные фиксированные расходы",
    "uk": "Введені постійні витрати",
    "zh": "已输入的固定支出",
    "zh_TW": "已輸入的固定支出",
    "vi": "Chi phí cố định đã nhập"
  },
  "onboardingPreviewLeft": {
    "en": "Left for day-to-day + goals",
    "de": "Rest für Alltag + Ziele",
    "es": "Restante para el día a día y metas",
    "fr": "Reste pour le quotidien + objectifs",
    "it": "Rimanente per spese quotidiane + obiettivi",
    "ja": "生活費＋目標に回せる額",
    "kr": "생활비 + 목표를 위해 남은 금액",
    "nl": "Beschikbaar voor dagelijks gebruik + doelen",
    "ur": "روزمرہ کے اخراجات + اہداف کے لیے باقی رقم",
    "ru": "Остаток на жизнь и цели",
    "uk": "Залишок на щоденні витрати + цілі",
    "zh": "剩余可用资金（日常+目标）",
    "zh_TW": "剩餘可用資金（日常+目標）",
    "vi": "Còn lại cho chi tiêu hàng ngày + mục tiêu"
  },
  "onboardingPreviewFixedTooHigh": {
    "en": "Your fixed costs are higher than your total. Increase your total or lower a fixed amount to continue.",
    "de": "Deine Fixkosten sind höher als dein Budget. Erhöhe das Budget oder senke die Fixkosten.",
    "es": "Tus gastos fijos superan el total. Aumenta el total o reduce un gasto fijo para continuar.",
    "fr": "Vos frais fixes sont supérieurs à votre total. Augmentez le total ou baissez un montant fixe pour continuer.",
    "it": "Le tue spese fisse superano il totale. Aumenta il totale o riduci una spesa fissa per continuare.",
    "ja": "固定費の合計が予算を超えています。続行するには予算を増やすか、固定費を減らしてください。",
    "kr": "고정 지출이 총 금액보다 많습니다. 계속하려면 총 금액을 늘리거나 고정 지출을 줄여주세요.",
    "nl": "Je vaste lasten zijn hoger dan je totaal. Verhoog je totaal of verlaag een vast bedrag om door te gaan.",
    "ur": "آپ کے مقررہ اخراجات کل رقم سے زیادہ ہیں۔ جاری رکھنے کے لیے کل رقم بڑھائیں یا مقررہ رقم کم کریں۔",
    "ru": "Фиксированные расходы превышают бюджет. Увеличьте общую сумму или уменьшите расходы, чтобы продолжить.",
    "uk": "Ваші постійні витрати перевищують загальну суму. Збільште загальну суму або зменште витрати, щоб продовжити.",
    "zh": "您的固定支出超过了总金额。请增加总金额或降低固定金额以继续。",
    "zh_TW": "您的固定支出超過了總金額。請增加總金額或降低固定金額以繼續。",
    "vi": "Chi phí cố định cao hơn tổng số tiền của bạn. Hãy tăng tổng tiền hoặc giảm chi phí cố định để tiếp tục."
  },
  "onboardingPreviewTightRemainder": {
    "en": "This is tight for day-to-day spending. Consider reducing savings/debt extras or increasing your total.",
    "de": "Das ist knapp für den Alltag. Überlege, Sparziele zu kürzen oder dein Budget zu erhöhen.",
    "es": "El margen para el día a día es muy ajustado. Considera reducir el ahorro, el pago de deudas o aumentar el total.",
    "fr": "C'est un peu serré pour le quotidien. Pensez à réduire l'épargne ou à augmenter votre total.",
    "it": "Margine ridotto per le spese quotidiane. Considera di ridurre i risparmi o aumentare il totale.",
    "ja": "生活費に余裕がありません。貯金額を減らすか、予算を増やすことを検討してください。",
    "kr": "생활비로 쓰기에 빠듯합니다. 저축을 줄이거나 총 금액을 늘리는 것을 고려해 보세요.",
    "nl": "Dit is krap voor dagelijkse uitgaven. Overweeg je besparingen te verlagen of je totaal te verhogen.",
    "ur": "یہ روزمرہ کے اخراجات کے لیے کم ہے۔ بچت کم کرنے یا کل رقم بڑھانے پر غور کریں۔",
    "ru": "Маловато для повседневных трат. Попробуйте сократить накопления или увеличить общую сумму.",
    "uk": "Цього замало для щоденних витрат. Спробуйте зменшити суму заощаджень або збільшити загальну суму.",
    "zh": "日常开支较为紧促。建议减少储蓄/额外还债，或增加总金额。",
    "zh_TW": "日常開支較為緊促。建議減少儲蓄/額外還債，或增加總金額。",
    "vi": "Số tiền còn lại khá ít cho chi tiêu hàng ngày. Hãy cân nhắc giảm tiết kiệm hoặc tăng tổng tiền."
  },
  "importAutoMappedBanner": {
    "en": "Column mapping was auto-detected with high confidence",
    "de": "Spaltenzuordnung wurde automatisch erkannt",
    "es": "Asignación de columnas detectada automáticamente",
    "fr": "Le mappage des colonnes a été détecté automatiquement",
    "it": "Mappatura delle colonne rilevata automaticamente",
    "ja": "列のマッピングが自動検出されました",
    "kr": "열 매핑이 자동으로 감지되었습니다",
    "nl": "Kolomtoewijzing is automatisch gedetecteerd",
    "ur": "کالم میپنگ کی خود بخود شناخت ہو گئی ہے",
    "ru": "Сопоставление колонок определено автоматически",
    "uk": "Співставлення стовпців визначено автоматично",
    "zh": "已自动检测到高度准确的列映射",
    "zh_TW": "已自動檢測到高度準確的欄位映射",
    "vi": "Đã tự động nhận diện ánh xạ cột với độ chính xác cao"
  },
  "importReviewMapping": {
    "en": "Review mapping",
    "de": "Zuordnung prüfen",
    "es": "Revisar asignación",
    "fr": "Vérifier le mappage",
    "it": "Rivedi mappatura",
    "ja": "マッピングを確認",
    "kr": "매핑 검토",
    "nl": "Toewijzing controleren",
    "ur": "میپنگ کا جائزہ لیں",
    "ru": "Проверить сопоставление",
    "uk": "Перевірити співставлення",
    "zh": "检查映射",
    "zh_TW": "檢查映射",
    "vi": "Kiểm tra ánh xạ"
  },
  "importIssueInvalidDate": {
    "en": "Bad date",
    "de": "Falsches Datum",
    "es": "Fecha inválida",
    "fr": "Date invalide",
    "it": "Data errata",
    "ja": "日付の不備",
    "kr": "날짜 오류",
    "nl": "Onjuiste datum",
    "ur": "غلط تاریخ",
    "ru": "Некорректная дата",
    "uk": "Невірна дата",
    "zh": "日期错误",
    "zh_TW": "日期錯誤",
    "vi": "Ngày không hợp lệ"
  },
  "importIssueInvalidAmount": {
    "en": "Bad amount",
    "de": "Falscher Betrag",
    "es": "Monto inválido",
    "fr": "Montant invalide",
    "it": "Importo errato",
    "ja": "金額の不備",
    "kr": "금액 오류",
    "nl": "Onjuist bedrag",
    "ur": "غلط رقم",
    "ru": "Ошибка в сумме",
    "uk": "Невірна сума",
    "zh": "金额错误",
    "zh_TW": "金額錯誤",
    "vi": "Số tiền không hợp lệ"
  },
  "importIssueMissingCurrency": {
    "en": "No currency",
    "de": "Keine Währung",
    "es": "Sin divisa",
    "fr": "Pas de devise",
    "it": "Valuta mancante",
    "ja": "通貨なし",
    "kr": "통화 없음",
    "nl": "Geen valuta",
    "ur": "کوئی کرنسی نہیں",
    "ru": "Валюта не указана",
    "uk": "Валюту не вказано",
    "zh": "缺失币种",
    "zh_TW": "缺失幣別",
    "vi": "Thiếu đơn vị tiền tệ"
  },
  "importIssueUnknownType": {
    "en": "No type",
    "de": "Kein Typ",
    "es": "Sin tipo",
    "fr": "Pas de type",
    "it": "Tipo mancante",
    "ja": "タイプなし",
    "kr": "유형 없음",
    "nl": "Geen type",
    "ur": "کوئی قسم نہیں",
    "ru": "Тип не указан",
    "uk": "Тип не вказано",
    "zh": "缺失类型",
    "zh_TW": "缺失類型",
    "vi": "Thiếu loại"
  },
  "importIssueLowConfidence": {
    "en": "Low confidence",
    "de": "Unsicher",
    "es": "Poca confianza",
    "fr": "Confiance faible",
    "it": "Bassa precisione",
    "ja": "低い信頼度",
    "kr": "정확도 낮음",
    "nl": "Lage zekerheid",
    "ur": "کم اعتماد",
    "ru": "Низкая точность",
    "uk": "Низька точність",
    "zh": "置信度低",
    "zh_TW": "信心度低",
    "vi": "Độ tin cậy thấp"
  },
  "importDuplicateInFile": {
    "en": "Dupe (file)",
    "de": "Duplikat (Datei)",
    "es": "Duplicado (archivo)",
    "fr": "Doublon (fichier)",
    "it": "Duplicato (file)",
    "ja": "重複（ファイル内）",
    "kr": "중복 (파일)",
    "nl": "Duplicaat (bestand)",
    "ur": "ڈپلیکیٹ (فائل)",
    "ru": "Повтор (в файле)",
    "uk": "Дублікат (у файлі)",
    "zh": "重复（文件内）",
    "zh_TW": "重複（檔案內）",
    "vi": "Trùng (tệp)"
  },
  "importDuplicateInDb": {
    "en": "Dupe (existing)",
    "de": "Duplikat (vorhanden)",
    "es": "Duplicado (existente)",
    "fr": "Doublon (existant)",
    "it": "Duplicato (esistente)",
    "ja": "重複（既存）",
    "kr": "중복 (기존)",
    "nl": "Duplicaat (bestaand)",
    "ur": "ڈپلیکیٹ (موجودہ)",
    "ru": "Повтор (уже есть)",
    "uk": "Дублікат (наявний)",
    "zh": "重复（已存在）",
    "zh_TW": "重複（已存在）",
    "vi": "Trùng (đã có)"
  },
  "importEditCurrencyHint": {
    "en": "e.g. USD, EUR",
    "de": "z. B. USD, EUR",
    "es": "ej. USD, EUR",
    "fr": "ex. USD, EUR",
    "it": "es. USD, EUR",
    "ja": "例：JPY, USD",
    "kr": "예: KRW, USD",
    "nl": "bijv. EUR, USD",
    "ur": "مثلاً USD, EUR",
    "ru": "напр. RUB, USD",
    "uk": "напр. UAH, USD",
    "zh": "例如：CNY, USD",
    "zh_TW": "例如：TWD, USD",
    "vi": "vd: VND, USD"
  },
  "importEditTypeLabel": {
    "en": "Transaction type",
    "de": "Transaktionstyp",
    "es": "Tipo de transacción",
    "fr": "Type de transaction",
    "it": "Tipo di transazione",
    "ja": "取引タイプ",
    "kr": "거래 유형",
    "nl": "Transactietype",
    "ur": "لین دین کی قسم",
    "ru": "Тип транзакции",
    "uk": "Тип транзакції",
    "zh": "交易类型",
    "zh_TW": "交易類型",
    "vi": "Loại giao dịch"
  },
  "importPartialSuccess": {
    "en": "Imported {succeeded}, {failed} failed",
    "de": "",
    "es": "",
    "fr": "",
    "it": "",
    "ja": "",
    "kr": "",
    "nl": "",
    "ur": "",
    "ru": "",
    "uk": "",
    "zh": "",
    "zh_TW": "",
    "vi": ""
  },
  "importAllFailed": {
    "en": "Import failed: {failed} errors",
    "de": "",
    "es": "",
    "fr": "",
    "it": "",
    "ja": "",
    "kr": "",
    "nl": "",
    "ur": "",
    "ru": "",
    "uk": "",
    "zh": "",
    "zh_TW": "",
    "vi": ""
  }
}
