{
"couldNotLoadMonthlyFinancialHealth": {
"en": "Could not load monthly financial health: {error}",
"de": "Monatliche Finanzgesundheit konnte nicht geladen werden: {error}",
"es": "No se pudo cargar la salud financiera mensual: {error}",
"fr": "Impossible de charger la santé financière mensuelle : {error}",
"it": "Impossibile caricare la salute finanziaria mensile: {error}",
"ja": "月間の家計健全性を読み込めませんでした: {error}",
"ko": "월간 재정 건강도를 불러올 수 없습니다: {error}",
"nl": "Kon maandelijkse financiële gezondheid niet laden: {error}",
"ur": "ماہانہ مالی صحت لوڈ نہیں ہو سکی: {error}",
"ru": "Не удалось загрузить финансовое состояние за месяц: {error}",
"th": "ไม่สามารถโหลดสุขภาพทางการเงินรายเดือนได้: {error}",
"uk": "Не вдалося завантажити фінансовий стан за місяць: {error}",
"zh": "无法加载月度财务健康：{error}",
"zh_TW": "無法載入月度財務健康：{error}",
"vi": "Không thể tải sức khỏe tài chính hằng tháng: {error}"
},
"month": {
"en": "Month",
"de": "Monat",
"es": "Mes",
"fr": "Mois",
"it": "Mese",
"ja": "月",
"ko": "월",
"nl": "Maand",
"ur": "مہینہ",
"ru": "Месяц",
"th": "เดือน",
"uk": "Місяць",
"zh": "月份",
"zh_TW": "月份",
"vi": "Tháng"
},
"couldNotLoadReport": {
"en": "Could not load report: {error}",
"de": "Bericht konnte nicht geladen werden: {error}",
"es": "No se pudo cargar el informe: {error}",
"fr": "Impossible de charger le rapport : {error}",
"it": "Impossibile caricare il report: {error}",
"ja": "レポートを読み込めませんでした: {error}",
"ko": "보고서를 불러올 수 없습니다: {error}",
"nl": "Kon rapport niet laden: {error}",
"ur": "رپورٹ لوڈ نہیں ہو سکی: {error}",
"ru": "Не удалось загрузить отчёт: {error}",
"th": "ไม่สามารถโหลดรายงานได้: {error}",
"uk": "Не вдалося завантажити звіт: {error}",
"zh": "无法加载报告：{error}",
"zh_TW": "無法載入報告：{error}",
"vi": "Không thể tải báo cáo: {error}"
},
"forecastLabel": {
"en": "Forecast {amount}",
"de": "Prognose {amount}",
"es": "Previsión {amount}",
"fr": "Prévision {amount}",
"it": "Previsione {amount}",
"ja": "予測 {amount}",
"ko": "예상 {amount}",
"nl": "Prognose {amount}",
"ur": "پیش گوئی {amount}",
"ru": "Прогноз {amount}",
"th": "คาดการณ์ {amount}",
"uk": "Прогноз {amount}",
"zh": "预测 {amount}",
"zh_TW": "預測 {amount}",
"vi": "Dự báo {amount}"
},
"fromLastSnapshot": {
"en": "from last snapshot",
"de": "seit der letzten Momentaufnahme",
"es": "desde la última instantánea",
"fr": "depuis le dernier instantané",
"it": "dall’ultima istantanea",
"ja": "前回のスナップショットから",
"ko": "마지막 스냅샷 이후",
"nl": "sinds de laatste momentopname",
"ur": "آخری اسنیپ شاٹ سے",
"ru": "с последнего снимка",
"th": "จากภาพรวมล่าสุด",
"uk": "з останнього знімка",
"zh": "较上次快照",
"zh_TW": "較上次快照",
"vi": "so với ảnh chụp gần nhất"
},
"noProjectedLowDate": {
"en": "No projected low date",
"de": "Kein prognostiziertes Tiefdatum",
"es": "Sin fecha mínima prevista",
"fr": "Aucune date basse prévue",
"it": "Nessuna data minima prevista",
"ja": "予測される最低日のデータなし",
"ko": "예상 최저 날짜 없음",
"nl": "Geen verwachte laagste datum",
"ur": "کوئی متوقع کم ترین تاریخ نہیں",
"ru": "Нет прогнозируемой даты минимума",
"th": "ไม่มีวันที่คาดว่าจะต่ำสุด",
"uk": "Немає прогнозованої дати мінімуму",
"zh": "暂无预计低点日期",
"zh_TW": "暫無預計低點日期",
"vi": "Chưa có ngày thấp nhất dự kiến"
},
"billsAppearCovered": {
"en": "Bills appear covered",
"de": "Rechnungen scheinen gedeckt zu sein",
"es": "Las facturas parecen cubiertas",
"fr": "Les factures semblent couvertes",
"it": "Le bollette sembrano coperte",
"ja": "請求分はカバーできそうです",
"ko": "청구서는 충당될 것으로 보여요",
"nl": "Rekeningen lijken gedekt",
"ur": "بل ادا ہوتے نظر آ رہے ہیں",
"ru": "Похоже, счета покрыты",
"th": "ดูเหมือนว่าบิลจะครอบคลุมแล้ว",
"uk": "Схоже, рахунки покриті",
"zh": "账单似乎已覆盖",
"zh_TW": "帳單似乎已涵蓋",
"vi": "Có vẻ hóa đơn đã được đảm bảo"
},
"balanceMayGoNegative": {
"en": "Balance may go negative",
"de": "Der Kontostand könnte ins Minus rutschen",
"es": "El saldo podría quedar en negativo",
"fr": "Le solde pourrait devenir négatif",
"it": "Il saldo potrebbe andare in negativo",
"ja": "残高がマイナスになる可能性があります",
"ko": "잔액이 마이너스가 될 수 있어요",
"nl": "Saldo kan negatief worden",
"ur": "بیلنس منفی ہو سکتا ہے",
"ru": "Баланс может уйти в минус",
"th": "ยอดคงเหลืออาจติดลบ",
"uk": "Баланс може стати від’ємним",
"zh": "余额可能变为负数",
"zh_TW": "餘額可能變成負數",
"vi": "Số dư có thể bị âm"
},
"daysRemainingLabel": {
"en": "{count} days remaining",
"de": "Noch {count} Tage",
"es": "Quedan {count} días",
"fr": "{count} jours restants",
"it": "{count} giorni rimanenti",
"ja": "残り{count}日",
"ko": "{count}일 남음",
"nl": "Nog {count} dagen",
"ur": "{count} دن باقی",
"ru": "Осталось {count} дн.",
"th": "เหลืออีก {count} วัน",
"uk": "Залишилося {count} дн.",
"zh": "剩余 {count} 天",
"zh_TW": "剩餘 {count} 天",
"vi": "Còn {count} ngày"
},
"vsLastMonth": {
"en": "{amount} vs last month",
"de": "{amount} gegenüber letztem Monat",
"es": "{amount} vs. el mes pasado",
"fr": "{amount} par rapport au mois dernier",
"it": "{amount} rispetto al mese scorso",
"ja": "先月比 {amount}",
"ko": "지난달 대비 {amount}",
"nl": "{amount} t.o.v. vorige maand",
"ur": "پچھلے ماہ کے مقابلے {amount}",
"ru": "{amount} к прошлому месяцу",
"th": "{amount} เทียบกับเดือนที่แล้ว",
"uk": "{amount} порівняно з минулим місяцем",
"zh": "较上月 {amount}",
"zh_TW": "較上月 {amount}",
"vi": "{amount} so với tháng trước"
},
"patternCheck": {
"en": "Pattern Check",
"de": "Musterprüfung",
"es": "Revisión de patrones",
"fr": "Analyse des habitudes",
"it": "Controllo delle abitudini",
"ja": "パターン確認",
"ko": "패턴 확인",
"nl": "Patrooncontrole",
"ur": "رجحان کی جانچ",
"ru": "Проверка закономерностей",
"th": "ตรวจสอบรูปแบบ",
"uk": "Перевірка закономірностей",
"zh": "模式检查",
"zh_TW": "模式檢查",
"vi": "Kiểm tra xu hướng"
},
"categoryNeedsAttention": {
"en": "{category} needs attention.",
"de": "{category} braucht Aufmerksamkeit.",
"es": "{category} necesita atención.",
"fr": "{category} mérite votre attention.",
"it": "{category} richiede attenzione.",
"ja": "{category}の確認が必要です。",
"ko": "{category} 확인이 필요합니다.",
"nl": "{category} heeft aandacht nodig.",
"ur": "{category} پر توجہ درکار ہے۔",
"ru": "{category} требует внимания.",
"th": "{category} ต้องตรวจสอบ",
"uk": "{category} потребує уваги.",
"zh": "{category} 需要关注。",
"zh_TW": "{category} 需要留意。",
"vi": "{category} cần được chú ý."
},
"categoriesNeedAttention": {
"en": "{count} categories need attention.",
"de": "{count} Kategorien brauchen Aufmerksamkeit.",
"es": "{count} categorías necesitan atención.",
"fr": "{count} catégories méritent votre attention.",
"it": "{count} categorie richiedono attenzione.",
"ja": "{count}件のカテゴリで確認が必要です。",
"ko": "{count}개 카테고리 확인이 필요합니다.",
"nl": "{count} categorieën hebben aandacht nodig.",
"ur": "{count} زمروں پر توجہ درکار ہے۔",
"ru": "{count} категорий требуют внимания.",
"th": "มี {count} หมวดที่ต้องตรวจสอบ",
"uk": "{count} категорій потребують уваги.",
"zh": "{count} 个类别需要关注。",
"zh_TW": "{count} 個類別需要留意。",
"vi": "{count} danh mục cần được chú ý."
},
"rateLabel": {
"en": "{value} rate",
"de": "{value}-Rate",
"es": "Tasa {value}",
"fr": "Taux {value}",
"it": "Tasso {value}",
"ja": "{value}率",
"ko": "{value} 비율",
"nl": "{value}-percentage",
"ur": "{value} شرح",
"ru": "Показатель {value}",
"th": "อัตรา {value}",
"uk": "Рівень {value}",
"zh": "{value}率",
"zh_TW": "{value}率",
"vi": "Tỷ lệ {value}"
},
"positiveForecast": {
"en": "Positive forecast",
"de": "Positive Prognose",
"es": "Previsión positiva",
"fr": "Prévision positive",
"it": "Previsione positiva",
"ja": "プラス予測",
"ko": "긍정적인 예측",
"nl": "Positieve prognose",
"ur": "مثبت پیش گوئی",
"ru": "Положительный прогноз",
"th": "คาดการณ์เป็นบวก",
"uk": "Позитивний прогноз",
"zh": "正向预测",
"zh_TW": "正向預測",
"vi": "Dự báo tích cực"
},
"negativeForecast": {
"en": "Negative forecast",
"de": "Negative Prognose",
"es": "Previsión negativa",
"fr": "Prévision négative",
"it": "Previsione negativa",
"ja": "マイナス予測",
"ko": "부정적인 예측",
"nl": "Negatieve prognose",
"ur": "منفی پیش گوئی",
"ru": "Отрицательный прогноз",
"th": "คาดการณ์เป็นลบ",
"uk": "Негативний прогноз",
"zh": "负向预测",
"zh_TW": "負向預測",
"vi": "Dự báo tiêu cực"
},
"buildingRoom": {
"en": "Building room",
"de": "Spielraum aufbauen",
"es": "Creando margen",
"fr": "Création de marge",
"it": "Creazione di margine",
"ja": "余裕を作っています",
"ko": "여유를 만드는 중",
"nl": "Ruimte opbouwen",
"ur": "گنجائش بن رہی ہے",
"ru": "Создаётся запас",
"th": "กำลังสร้างพื้นที่เผื่อ",
"uk": "Створюється запас",
"zh": "正在建立余地",
"zh_TW": "正在建立餘裕",
"vi": "Đang tạo thêm dư địa"
},
"usingBuffer": {
"en": "Using buffer",
"de": "Puffer wird genutzt",
"es": "Usando el colchón",
"fr": "Utilisation de la marge",
"it": "Uso del margine",
"ja": "余裕資金を使用中",
"ko": "여유 자금 사용 중",
"nl": "Buffer gebruiken",
"ur": "بفر استعمال ہو رہا ہے",
"ru": "Используется резерв",
"th": "กำลังใช้เงินสำรอง",
"uk": "Використовується резерв",
"zh": "正在动用缓冲资金",
"zh_TW": "正在動用緩衝資金",
"vi": "Đang dùng khoản dự phòng"
},
"goalProgressDetail": {
"en": "{current} / {target} · {needed}/mo needed",
"de": "{current} / {target} · {needed}/Monat benötigt",
"es": "{current} / {target} · se necesitan {needed}/mes",
"fr": "{current} / {target} · {needed}/mois nécessaires",
"it": "{current} / {target} · servono {needed}/mese",
"ja": "{current} / {target} · 月{needed}が必要",
"ko": "{current} / {target} · 월 {needed} 필요",
"nl": "{current} / {target} · {needed}/mnd nodig",
"ur": "{current} / {target} · ہر ماہ {needed} درکار",
"ru": "{current} / {target} · нужно {needed}/мес.",
"th": "{current} / {target} · ต้องการ {needed}/เดือน",
"uk": "{current} / {target} · потрібно {needed}/міс.",
"zh": "{current} / {target} · 每月需 {needed}",
"zh_TW": "{current} / {target} · 每月需 {needed}",
"vi": "{current} / {target} · cần {needed}/tháng"
},
"moreHistoryNeeded": {
"en": "More history is needed.",
"de": "Es wird mehr Verlauf benötigt.",
"es": "Se necesita más historial.",
"fr": "Plus d’historique est nécessaire.",
"it": "Serve più storico.",
"ja": "もう少し履歴が必要です。",
"ko": "더 많은 기록이 필요합니다.",
"nl": "Er is meer historie nodig.",
"ur": "مزید سابقہ ریکارڈ درکار ہے۔",
"ru": "Нужно больше данных.",
"th": "ต้องมีประวัติเพิ่มเติม",
"uk": "Потрібно більше історії.",
"zh": "需要更多历史数据。",
"zh_TW": "需要更多歷史資料。",
"vi": "Cần thêm dữ liệu lịch sử."
},
"balance": {
"en": "Balance",
"de": "Saldo",
"es": "Saldo",
"fr": "Solde",
"it": "Saldo",
"ja": "残高",
"ko": "잔액",
"nl": "Saldo",
"ur": "بیلنس",
"ru": "Баланс",
"th": "ยอดคงเหลือ",
"uk": "Баланс",
"zh": "余额",
"zh_TW": "餘額",
"vi": "Số dư"
},
"safeToSpendLabel": {
"en": "Safe to Spend",
"de": "Sicher auszugeben",
"es": "Disponible para gastar",
"fr": "Montant sûr à dépenser",
"it": "Quanto puoi spendere",
"ja": "使っても安心な金額",
"ko": "안심 지출 가능액",
"nl": "Veilig te besteden",
"ur": "خرچ کے لیے محفوظ",
"ru": "Безопасная сумма для трат",
"th": "ยอดที่ใช้ได้อย่างปลอดภัย",
"uk": "Безпечна сума для витрат",
"zh": "可安心支出",
"zh_TW": "可安心支出",
"vi": "Số tiền an toàn để chi"
},
"spendingLabel": {
"en": "Spending",
"de": "Ausgaben",
"es": "Gastos",
"fr": "Dépenses",
"it": "Spese",
"ja": "支出",
"ko": "지출",
"nl": "Uitgaven",
"ur": "اخراجات",
"ru": "Расходы",
"th": "รายจ่าย",
"uk": "Витрати",
"zh": "支出",
"zh_TW": "支出",
"vi": "Chi tiêu"
},
"budgetLabel": {
"en": "Budget",
"de": "Budget",
"es": "Presupuesto",
"fr": "Budget",
"it": "Budget",
"ja": "予算",
"ko": "예산",
"nl": "Budget",
"ur": "بجٹ",
"ru": "Бюджет",
"th": "งบประมาณ",
"uk": "Бюджет",
"zh": "预算",
"zh_TW": "預算",
"vi": "Ngân sách"
},
"savingsLabel": {
"en": "Savings",
"de": "Ersparnisse",
"es": "Ahorros",
"fr": "Épargne",
"it": "Risparmi",
"ja": "貯蓄",
"ko": "저축",
"nl": "Spaargeld",
"ur": "بچت",
"ru": "Сбережения",
"th": "เงินออม",
"uk": "Заощадження",
"zh": "储蓄",
"zh_TW": "儲蓄",
"vi": "Tiết kiệm"
},
"categoriesLabel": {
"en": "Categories",
"de": "Kategorien",
"es": "Categorías",
"fr": "Catégories",
"it": "Categorie",
"ja": "カテゴリ",
"ko": "카테고리",
"nl": "Categorieën",
"ur": "زمرے",
"ru": "Категории",
"th": "หมวดหมู่",
"uk": "Категорії",
"zh": "分类",
"zh_TW": "分類",
"vi": "Danh mục"
},
"recurringLabel": {
"en": "Recurring",
"de": "Wiederkehrend",
"es": "Recurrente",
"fr": "Récurrent",
"it": "Ricorrente",
"ja": "定期",
"ko": "반복",
"nl": "Terugkerend",
"ur": "بار بار آنے والا",
"ru": "Регулярные",
"th": "รายการประจำ",
"uk": "Регулярні",
"zh": "周期性",
"zh_TW": "週期性",
"vi": "Định kỳ"
},
"noBaseline": {
"en": "No baseline",
"de": "Keine Basislinie",
"es": "Sin referencia",
"fr": "Aucune référence",
"it": "Nessun riferimento",
"ja": "基準データなし",
"ko": "기준 없음",
"nl": "Geen basislijn",
"ur": "کوئی بنیادی معیار نہیں",
"ru": "Нет базового уровня",
"th": "ไม่มีข้อมูลอ้างอิง",
"uk": "Немає базового рівня",
"zh": "暂无基准",
"zh_TW": "暫無基準",
"vi": "Chưa có mốc so sánh"
},
"spentLabel": {
"en": "{amount} spent",
"de": "{amount} ausgegeben",
"es": "{amount} gastado",
"fr": "{amount} dépensé",
"it": "{amount} speso",
"ja": "{amount}使用済み",
"ko": "{amount} 지출",
"nl": "{amount} uitgegeven",
"ur": "{amount} خرچ",
"ru": "Потрачено {amount}",
"th": "ใช้ไป {amount}",
"uk": "Витрачено {amount}",
"zh": "已支出 {amount}",
"zh_TW": "已支出 {amount}",
"vi": "Đã chi {amount}"
},
"higherThanComparison": {
"en": "{percent}% higher than comparison.",
"de": "{percent}% höher als der Vergleichswert.",
"es": "{percent}% más alto que la referencia.",
"fr": "{percent} % au-dessus de la référence.",
"it": "{percent}% in più rispetto al confronto.",
"ja": "比較対象より{percent}%高いです。",
"ko": "비교 기준보다 {percent}% 높습니다.",
"nl": "{percent}% hoger dan de vergelijking.",
"ur": "موازنہ کے مقابلے میں {percent}% زیادہ۔",
"ru": "На {percent}% выше сравнения.",
"th": "สูงกว่าค่าเปรียบเทียบ {percent}%",
"uk": "На {percent}% вище за порівняння.",
"zh": "比对比值高 {percent}%。",
"zh_TW": "比對比值高 {percent}%。",
"vi": "Cao hơn {percent}% so với mức so sánh."
},
"lowerThanComparison": {
"en": "{percent}% lower than comparison.",
"de": "{percent}% niedriger als der Vergleichswert.",
"es": "{percent}% más bajo que la referencia.",
"fr": "{percent} % en dessous de la référence.",
"it": "{percent}% in meno rispetto al confronto.",
"ja": "比較対象より{percent}%低いです。",
"ko": "비교 기준보다 {percent}% 낮습니다.",
"nl": "{percent}% lager dan de vergelijking.",
"ur": "موازنہ کے مقابلے میں {percent}% کم۔",
"ru": "На {percent}% ниже сравнения.",
"th": "ต่ำกว่าค่าเปรียบเทียบ {percent}%",
"uk": "На {percent}% нижче за порівняння.",
"zh": "比对比值低 {percent}%。",
"zh_TW": "比對比值低 {percent}%。",
"vi": "Thấp hơn {percent}% so với mức so sánh."
},
"monthOnTrack": {
"en": "Your month is mostly on track.",
"de": "Dein Monat ist größtenteils im Plan.",
"es": "Tu mes va mayormente por buen camino.",
"fr": "Votre mois est globalement sur la bonne voie.",
"it": "Il tuo mese è per lo più in linea.",
"ja": "今月はおおむね順調です。",
"ko": "이번 달은 대체로 계획대로 진행 중입니다.",
"nl": "Je maand ligt grotendeels op schema.",
"ur": "آپ کا مہینہ زیادہ تر درست سمت میں ہے۔",
"ru": "Ваш месяц в целом идёт по плану.",
"th": "เดือนนี้ของคุณโดยรวมยังเป็นไปตามแผน",
"uk": "Ваш місяць загалом іде за планом.",
"zh": "你这个月整体进展正常。",
"zh_TW": "你這個月整體進展正常。",
"vi": "Tháng này của bạn nhìn chung đang đi đúng hướng."
},
"spendingMovingFast": {
"en": "Your spending is moving a little fast.",
"de": "Deine Ausgaben steigen etwas zu schnell.",
"es": "Tus gastos están avanzando un poco rápido.",
"fr": "Vos dépenses augmentent un peu vite.",
"it": "Le tue spese stanno andando un po’ troppo veloci.",
"ja": "支出のペースが少し速くなっています。",
"ko": "지출 속도가 조금 빠릅니다.",
"nl": "Je uitgaven lopen wat snel op.",
"ur": "آپ کا خرچ کچھ تیزی سے بڑھ رہا ہے۔",
"ru": "Ваши расходы растут немного быстрее обычного.",
"th": "การใช้จ่ายของคุณค่อนข้างเร็วไปเล็กน้อย",
"uk": "Ваші витрати зростають трохи швидко.",
"zh": "你的支出速度有点快。",
"zh_TW": "你的支出速度有點快。",
"vi": "Chi tiêu của bạn đang tăng hơi nhanh."
},
"monthNeedsAdjustment": {
"en": "Your month needs a small adjustment.",
"de": "Dein Monat braucht eine kleine Anpassung.",
"es": "Tu mes necesita un pequeño ajuste.",
"fr": "Votre mois nécessite un petit ajustement.",
"it": "Il tuo mese ha bisogno di un piccolo aggiustamento.",
"ja": "今月は少し調整が必要です。",
"ko": "이번 달은 작은 조정이 필요합니다.",
"nl": "Je maand heeft een kleine aanpassing nodig.",
"ur": "آپ کے مہینے کو ایک چھوٹی سی تبدیلی کی ضرورت ہے۔",
"ru": "Вашему месяцу нужна небольшая корректировка.",
"th": "เดือนนี้ของคุณต้องปรับเล็กน้อย",
"uk": "Ваш місяць потребує невеликого коригування.",
"zh": "你这个月需要做一点小调整。",
"zh_TW": "你這個月需要做一點小調整。",
"vi": "Tháng này của bạn cần một điều chỉnh nhỏ."
},
"budgetsNeedAttentionDetail": {
"en": "A few budgets need attention.",
"de": "Einige Budgets brauchen Aufmerksamkeit.",
"es": "Algunos presupuestos necesitan atención.",
"fr": "Quelques budgets méritent votre attention.",
"it": "Alcuni budget richiedono attenzione.",
"ja": "いくつかの予算で確認が必要です。",
"ko": "일부 예산 확인이 필요합니다.",
"nl": "Een paar budgetten hebben aandacht nodig.",
"ur": "کچھ بجٹس پر توجہ درکار ہے۔",
"ru": "Некоторые бюджеты требуют внимания.",
"th": "มีบางงบประมาณที่ต้องตรวจสอบ",
"uk": "Кілька бюджетів потребують уваги.",
"zh": "有几个预算需要关注。",
"zh_TW": "有幾個預算需要留意。",
"vi": "Một vài ngân sách cần được chú ý."
},
"spendingPatternsReview": {
"en": "There are spending patterns to review.",
"de": "Es gibt Ausgabemuster zu prüfen.",
"es": "Hay patrones de gasto por revisar.",
"fr": "Certains schémas de dépenses sont à examiner.",
"it": "Ci sono abitudini di spesa da rivedere.",
"ja": "確認すべき支出パターンがあります。",
"ko": "검토할 지출 패턴이 있습니다.",
"nl": "Er zijn uitgavenpatronen om te bekijken.",
"ur": "جائزہ لینے کے لیے خرچ کے کچھ رجحانات ہیں۔",
"ru": "Есть модели расходов, которые стоит проверить.",
"th": "มีรูปแบบการใช้จ่ายที่ควรตรวจสอบ",
"uk": "Є моделі витрат, які варто переглянути.",
"zh": "有一些支出模式需要查看。",
"zh_TW": "有一些支出模式需要查看。",
"vi": "Có một số xu hướng chi tiêu cần xem lại."
},
"budgetUsageDetail": {
"en": "{spentPercent}% used vs {timePercent}% month",
"de": "{spentPercent}% genutzt vs. {timePercent}% des Monats",
"es": "{spentPercent}% usado vs. {timePercent}% del mes",
"fr": "{spentPercent} % utilisé vs {timePercent} % du mois",
"it": "{spentPercent}% usato vs {timePercent}% del mese",
"ja": "{spentPercent}%使用済み / 月の経過{timePercent}%",
"ko": "{spentPercent}% 사용 vs 이번 달 {timePercent}% 경과",
"nl": "{spentPercent}% gebruikt vs {timePercent}% van de maand",
"ur": "{spentPercent}% استعمال بمقابلہ مہینے کا {timePercent}%",
"ru": "Использовано {spentPercent}% vs {timePercent}% месяца",
"th": "ใช้ไป {spentPercent}% เทียบกับเดือนที่ผ่านไป {timePercent}%",
"uk": "Використано {spentPercent}% vs {timePercent}% місяця",
"zh": "已用 {spentPercent}% / 本月已过 {timePercent}%",
"zh_TW": "已用 {spentPercent}% / 本月已過 {timePercent}%",
"vi": "Đã dùng {spentPercent}% so với {timePercent}% của tháng"
},
"onExpectedPace": {
"en": "On expected pace",
"de": "Im erwarteten Tempo",
"es": "Al ritmo esperado",
"fr": "Au rythme prévu",
"it": "In linea con il ritmo previsto",
"ja": "想定ペース内",
"ko": "예상 속도대로 진행 중",
"nl": "Op verwacht tempo",
"ur": "متوقع رفتار پر",
"ru": "В ожидаемом темпе",
"th": "เป็นไปตามจังหวะที่คาดไว้",
"uk": "В очікуваному темпі",
"zh": "符合预期进度",
"zh_TW": "符合預期進度",
"vi": "Đúng tiến độ dự kiến"
},
"billsCovered": {
"en": "Bills covered",
"de": "Rechnungen gedeckt",
"es": "Facturas cubiertas",
"fr": "Factures couvertes",
"it": "Bollette coperte",
"ja": "請求分を確保済み",
"ko": "청구서 충당됨",
"nl": "Rekeningen gedekt",
"ur": "بل کور ہو گئے",
"ru": "Счета покрыты",
"th": "ครอบคลุมบิลแล้ว",
"uk": "Рахунки покриті",
"zh": "账单已覆盖",
"zh_TW": "帳單已涵蓋",
"vi": "Hóa đơn đã được đảm bảo"
},
"scheduled": {
"en": "scheduled",
"de": "geplant",
"es": "programado",
"fr": "programmé",
"it": "programmato",
"ja": "予定済み",
"ko": "예정됨",
"nl": "gepland",
"ur": "شیڈول شدہ",
"ru": "запланировано",
"th": "กำหนดไว้แล้ว",
"uk": "заплановано",
"zh": "已安排",
"zh_TW": "已安排",
"vi": "đã lên lịch"
},
"coveredAhead": {
"en": "Covered ahead",
"de": "Im Voraus gedeckt",
"es": "Cubierto por adelantado",
"fr": "Couvert à l’avance",
"it": "Coperto in anticipo",
"ja": "先の分までカバー済み",
"ko": "미리 충당됨",
"nl": "Vooruit gedekt",
"ur": "آگے کے لیے کور شدہ",
"ru": "Покрыто заранее",
"th": "ครอบคลุมล่วงหน้า",
"uk": "Покрито наперед",
"zh": "已提前覆盖",
"zh_TW": "已提前涵蓋",
"vi": "Đã đảm bảo trước"
},
"needsCashFlow": {
"en": "Needs cash flow",
"de": "Braucht Cashflow",
"es": "Necesita flujo de caja",
"fr": "Besoin de trésorerie",
"it": "Serve flusso di cassa",
"ja": "キャッシュフローが必要",
"ko": "현금흐름 필요",
"nl": "Cashflow nodig",
"ur": "کیش فلو کی ضرورت ہے",
"ru": "Нужен денежный поток",
"th": "ต้องการกระแสเงินสด",
"uk": "Потрібен грошовий потік",
"zh": "需要现金流",
"zh_TW": "需要現金流",
"vi": "Cần dòng tiền"
},
"monthEndBuffer": {
"en": "Month-end buffer",
"de": "Puffer zum Monatsende",
"es": "Colchón de fin de mes",
"fr": "Marge de fin de mois",
"it": "Margine di fine mese",
"ja": "月末の余裕資金",
"ko": "월말 여유 자금",
"nl": "Buffer aan het einde van de maand",
"ur": "ماہ کے آخر کا بفر",
"ru": "Резерв на конец месяца",
"th": "เงินสำรองปลายเดือน",
"uk": "Резерв на кінець місяця",
"zh": "月末缓冲资金",
"zh_TW": "月底緩衝資金",
"vi": "Khoản dự phòng cuối tháng"
},
"buildingMonthlyReport": {
"en": "Building monthly report",
"de": "Monatsbericht wird erstellt",
"es": "Preparando informe mensual",
"fr": "Création du rapport mensuel",
"it": "Creazione del report mensile",
"ja": "月次レポートを作成中",
"ko": "월간 보고서 작성 중",
"nl": "Maandrapport opbouwen",
"ur": "ماہانہ رپورٹ بن رہی ہے",
"ru": "Формируем месячный отчёт",
"th": "กำลังสร้างรายงานรายเดือน",
"uk": "Формуємо місячний звіт",
"zh": "正在生成月度报告",
"zh_TW": "正在生成月度報告",
"vi": "Đang tạo báo cáo hằng tháng"
},
"checkingBudgetsTrends": {
"en": "Checking budgets, trends, and upcoming commitments.",
"de": "Budgets, Trends und anstehende Verpflichtungen werden geprüft.",
"es": "Revisando presupuestos, tendencias y compromisos próximos.",
"fr": "Vérification des budgets, tendances et engagements à venir.",
"it": "Controllo di budget, tendenze e impegni in arrivo.",
"ja": "予算、傾向、今後の支払い予定を確認しています。",
"ko": "예산, 추세, 다가오는 고정 지출을 확인 중입니다.",
"nl": "Budgetten, trends en aankomende verplichtingen controleren.",
"ur": "بجٹس، رجحانات اور آنے والی ذمہ داریوں کی جانچ ہو رہی ہے۔",
"ru": "Проверяем бюджеты, тренды и предстоящие обязательства.",
"th": "กำลังตรวจสอบงบประมาณ แนวโน้ม และภาระผูกพันที่กำลังจะมาถึง",
"uk": "Перевіряємо бюджети, тенденції та майбутні зобов’язання.",
"zh": "正在检查预算、趋势和即将到来的固定支出。",
"zh_TW": "正在檢查預算、趨勢和即將到來的固定支出。",
"vi": "Đang kiểm tra ngân sách, xu hướng và các cam kết sắp tới."
},
"reportReady": {
"en": "Report ready",
"de": "Bericht bereit",
"es": "Informe listo",
"fr": "Rapport prêt",
"it": "Report pronto",
"ja": "レポート準備完了",
"ko": "보고서 준비 완료",
"nl": "Rapport klaar",
"ur": "رپورٹ تیار ہے",
"ru": "Отчёт готов",
"th": "รายงานพร้อมแล้ว",
"uk": "Звіт готовий",
"zh": "报告已准备好",
"zh_TW": "報告已準備好",
"vi": "Báo cáo đã sẵn sàng"
},
"preparingProgress": {
"en": "Preparing {percent}%",
"de": "Vorbereitung {percent}%",
"es": "Preparando {percent}%",
"fr": "Préparation {percent} %",
"it": "Preparazione {percent}%",
"ja": "準備中 {percent}%",
"ko": "준비 중 {percent}%",
"nl": "Voorbereiden {percent}%",
"ur": "تیاری {percent}%",
"ru": "Подготовка {percent}%",
"th": "กำลังเตรียม {percent}%",
"uk": "Підготовка {percent}%",
"zh": "正在准备 {percent}%",
"zh_TW": "正在準備 {percent}%",
"vi": "Đang chuẩn bị {percent}%"
},
"refreshingReport": {
"en": "Refreshing report",
"de": "Bericht wird aktualisiert",
"es": "Actualizando informe",
"fr": "Actualisation du rapport",
"it": "Aggiornamento del report",
"ja": "レポートを更新中",
"ko": "보고서 새로고침 중",
"nl": "Rapport vernieuwen",
"ur": "رپورٹ ریفریش ہو رہی ہے",
"ru": "Обновляем отчёт",
"th": "กำลังรีเฟรชรายงาน",
"uk": "Оновлюємо звіт",
"zh": "正在刷新报告",
"zh_TW": "正在重新整理報告",
"vi": "Đang làm mới báo cáo"
},
"lastSyncedLabel": {
"en": "Last synced {time}",
"de": "Zuletzt synchronisiert {time}",
"es": "Última sincronización {time}",
"fr": "Dernière synchronisation {time}",
"it": "Ultima sincronizzazione {time}",
"ja": "最終同期 {time}",
"ko": "마지막 동기화 {time}",
"nl": "Laatst gesynchroniseerd {time}",
"ur": "آخری بار سنک ہوا {time}",
"ru": "Последняя синхронизация {time}",
"th": "ซิงค์ล่าสุด {time}",
"uk": "Остання синхронізація {time}",
"zh": "上次同步 {time}",
"zh_TW": "上次同步 {time}",
"vi": "Đồng bộ lần cuối {time}"
},
"never": {
"en": "never",
"de": "nie",
"es": "nunca",
"fr": "jamais",
"it": "mai",
"ja": "未同期",
"ko": "없음",
"nl": "nooit",
"ur": "کبھی نہیں",
"ru": "никогда",
"th": "ไม่เคย",
"uk": "ніколи",
"zh": "从未",
"zh_TW": "從未",
"vi": "chưa bao giờ"
},
"justNow": {
"en": "just now",
"de": "gerade eben",
"es": "ahora mismo",
"fr": "à l’instant",
"it": "proprio ora",
"ja": "たった今",
"ko": "방금",
"nl": "zojuist",
"ur": "ابھی ابھی",
"ru": "только что",
"th": "เมื่อสักครู่",
"uk": "щойно",
"zh": "刚刚",
"zh_TW": "剛剛",
"vi": "vừa xong"
},
"minutesAgo": {
"en": "{count} min{plural} ago",
"de": "vor {count} Min.",
"es": "hace {count} min",
"fr": "il y a {count} min",
"it": "{count} min fa",
"ja": "{count}分前",
"ko": "{count}분 전",
"nl": "{count} min geleden",
"ur": "{count} منٹ پہلے",
"ru": "{count} мин. назад",
"th": "{count} นาทีที่แล้ว",
"uk": "{count} хв тому",
"zh": "{count} 分钟前",
"zh_TW": "{count} 分鐘前",
"vi": "{count} phút trước"
},
"hoursAgo": {
"en": "{count} hour{plural} ago",
"de": "vor {count} Std.",
"es": "hace {count} h",
"fr": "il y a {count} h",
"it": "{count} h fa",
"ja": "{count}時間前",
"ko": "{count}시간 전",
"nl": "{count} uur geleden",
"ur": "{count} گھنٹے پہلے",
"ru": "{count} ч назад",
"th": "{count} ชั่วโมงที่แล้ว",
"uk": "{count} год тому",
"zh": "{count} 小时前",
"zh_TW": "{count} 小時前",
"vi": "{count} giờ trước"
},
"todayAtTime": {
"en": "today at {time}",
"de": "heute um {time}",
"es": "hoy a las {time}",
"fr": "aujourd’hui à {time}",
"it": "oggi alle {time}",
"ja": "今日 {time}",
"ko": "오늘 {time}",
"nl": "vandaag om {time}",
"ur": "آج {time} پر",
"ru": "сегодня в {time}",
"th": "วันนี้ เวลา {time}",
"uk": "сьогодні о {time}",
"zh": "今天 {time}",
"zh_TW": "今天 {time}",
"vi": "hôm nay lúc {time}"
},
"dateAtTime": {
"en": "{date} at {time}",
"de": "{date} um {time}",
"es": "{date} a las {time}",
"fr": "{date} à {time}",
"it": "{date} alle {time}",
"ja": "{date} {time}",
"ko": "{date} {time}",
"nl": "{date} om {time}",
"ur": "{date} کو {time} پر",
"ru": "{date} в {time}",
"th": "{date} เวลา {time}",
"uk": "{date} о {time}",
"zh": "{date} {time}",
"zh_TW": "{date} {time}",
"vi": "{date} lúc {time}"
},
"concentration": {
"en": "Concentration",
"de": "Konzentration",
"es": "Concentración",
"fr": "Concentration",
"it": "Concentrazione",
"ja": "集中度",
"ko": "집중도",
"nl": "Concentratie",
"ur": "ارتکاز",
"ru": "Концентрация",
"th": "ความกระจุกตัว",
"uk": "Концентрація",
"zh": "集中度",
"zh_TW": "集中度",
"vi": "Mức độ tập trung"
},
"percentOfSpending": {
"en": "{percent}% · {amount}",
"de": "{percent}% · {amount}",
"es": "{percent}% · {amount}",
"fr": "{percent} % · {amount}",
"it": "{percent}% · {amount}",
"ja": "{percent}% · {amount}",
"ko": "{percent}% · {amount}",
"nl": "{percent}% · {amount}",
"ur": "{percent}% · {amount}",
"ru": "{percent}% · {amount}",
"th": "{percent}% · {amount}",
"uk": "{percent}% · {amount}",
"zh": "{percent}% · {amount}",
"zh_TW": "{percent}% · {amount}",
"vi": "{percent}% · {amount}"
}
}
